metabase_pandas_api/__init__.py
metabase_pandas_api/metabase_pandas_api.py
metabase_pandas_api-1.4.0.dist-info/METADATA
metabase_pandas_api-1.4.0.dist-info/WHEEL
metabase_pandas_api-1.4.0.dist-info/top_level.txt
metabase_pandas_api-1.4.0.dist-info/RECORD
