Metadata-Version: 2.1
Name: metabase-pandas-api
Version: 1.4.0
Summary: A Python library for interacting with Metabase API
Home-page: https://github.com/fiatttkk/metabase-api
Author: Fiat
Author-email: fiat.ttkk@gmail.com
License: UNKNOWN
Platform: UNKNOWN
Classifier: Programming Language :: Python :: 3
Classifier: Operating System :: OS Independent
Requires-Python: >=3.6
Requires-Dist: requests
Requires-Dist: pandas
Requires-Dist: pytz
